agentic_doc/__init__.py
agentic_doc/common.py
agentic_doc/config.py
agentic_doc/connectors.py
agentic_doc/parse.py
agentic_doc/utils.py
agentic_doc-0.3.2.dist-info/LICENSE
agentic_doc-0.3.2.dist-info/METADATA
agentic_doc-0.3.2.dist-info/WHEEL
agentic_doc-0.3.2.dist-info/RECORD
