Metadata-Version: 2.1
Name: agentic-doc
Version: 0.3.2
Summary: A Python library that wraps around VisionAgent document extraction REST API to make documents extraction easy.
Author: Landing AI
Author-email: dev@landing.ai
Requires-Python: >=3.9,<4.0
Classifier: Programming Language :: Python :: 3
Classifier: Programming Language :: Python :: 3.9
Classifier: Programming Language :: Python :: 3.10
Classifier: Programming Language :: Python :: 3.11
Requires-Dist: boto3 (>=1.38.23,<2.0.0)
Requires-Dist: google-api-python-client (>=2.170.0,<3.0.0)
Requires-Dist: google-auth (>=2.40.2,<3.0.0)
Requires-Dist: google-auth-oauthlib (>=1.2.2,<2.0.0)
Requires-Dist: httpx (>=0.28.1,<0.29.0)
Requires-Dist: jsonschema (>=4.24.0,<5.0.0)
Requires-Dist: opencv-python-headless (>=4.11.0.86,<5.0.0.0)
Requires-Dist: pillow (>=10.0.0)
Requires-Dist: pillow-heif (>=0.17.0)
Requires-Dist: protobuf (>=6.31.1,<7.0.0)
Requires-Dist: pydantic (>=2.8.0)
Requires-Dist: pydantic-settings (>=2.2.1,<3.0.0)
Requires-Dist: pymupdf (>=1.25.5,<2.0.0)
Requires-Dist: pypdf (>=5.3.1,<6.0.0)
Requires-Dist: requests (>=2.32.4,<3.0.0)
Requires-Dist: structlog (>=25.2.0,<26.0.0)
Requires-Dist: tenacity (>=8.0.0)
Requires-Dist: tqdm (>=4.64.0,<5.0.0)
Requires-Dist: types-jsonschema (>=4.24.0.20250528,<5.0.0.0)
Requires-Dist: typing_extensions (>=4.0.0,<5.0.0)
Project-URL: Homepage, https://va.landing.ai/demo/doc-extraction
Project-URL: documentation, https://github.com/landing-ai/agentic-doc
Project-URL: repository, https://github.com/landing-ai/agentic-doc
